graphq_trans/__init__.py
graphq_trans/utils.py
graphq_trans/cypher/CypherLexer.py
graphq_trans/cypher/CypherParser.py
graphq_trans/cypher/CypherParserListener.py
graphq_trans/cypher/IREmitter.py
graphq_trans/cypher/parser.py
graphq_trans/cypher/translator.py
graphq_trans/cypher/utils.py
graphq_trans/ir/CypherEmitter.py
graphq_trans/ir/KoplEmitter.py
graphq_trans/ir/OvernightEmitter.py
graphq_trans/ir/SparqlEmitter.py
graphq_trans/ir/UnifiedIRLexer.py
graphq_trans/ir/UnifiedIRParser.py
graphq_trans/ir/UnifiedIRParserListener.py
graphq_trans/ir/misc.py
graphq_trans/ir/parser.py
graphq_trans/ir/translator.py
graphq_trans/ir/utils.py
graphq_trans/kopl/IREmitter.py
graphq_trans/kopl/KoplLexer.py
graphq_trans/kopl/KoplListener.py
graphq_trans/kopl/KoplParser.py
graphq_trans/kopl/__init__.py
graphq_trans/kopl/parser.py
graphq_trans/kopl/translator.py
graphq_trans/kopl/utils.py
graphq_trans/overnight/IREmitter.py
graphq_trans/overnight/OvernightLexer.py
graphq_trans/overnight/OvernightListener.py
graphq_trans/overnight/OvernightParser.py
graphq_trans/overnight/parser.py
graphq_trans/overnight/translator.py
graphq_trans/overnight/grammar/basketball.grammar
graphq_trans/overnight/grammar/blocks.grammar
graphq_trans/overnight/grammar/calendar.grammar
graphq_trans/overnight/grammar/housing.grammar
graphq_trans/overnight/grammar/publications.grammar
graphq_trans/overnight/grammar/recipes.grammar
graphq_trans/overnight/grammar/restaurants.grammar
graphq_trans/overnight/grammar/socialnetwork.grammar
graphq_trans/sparql/IREmitter.py
graphq_trans/sparql/SparqlLexer.py
graphq_trans/sparql/SparqlListener.py
graphq_trans/sparql/SparqlParser.py
graphq_trans/sparql/__init__.py
graphq_trans/sparql/parser.py
graphq_trans/sparql/translator.py
graphq_trans-0.1.0.dist-info/METADATA
graphq_trans-0.1.0.dist-info/WHEEL
graphq_trans-0.1.0.dist-info/top_level.txt
graphq_trans-0.1.0.dist-info/RECORD
