Metadata-Version: 2.1
Name: graphq-trans
Version: 0.1.0
Summary: A Graph Query Language Transpiler
Author-email: Lunyiu Nie <flitternie@gmail.com>, Jiuding Sun <jiuding.sun@gmail.com>
Project-URL: Homepage, https://github.com/Flitternie/GraphQ_Trans
Project-URL: Demo, https://graphqtrans.xlore.cn/
Classifier: Development Status :: 3 - Alpha
Classifier: Programming Language :: Python :: 3
Classifier: Operating System :: OS Independent
Classifier: License :: OSI Approved :: Apache Software License
Requires-Python: >=3.6
Requires-Dist: antlr4-python3-runtime (~=4.9.2)
